MANIFEST.in
README.rst
setup.py
apidev_djaloha.egg-info/PKG-INFO
apidev_djaloha.egg-info/SOURCES.txt
apidev_djaloha.egg-info/dependency_links.txt
apidev_djaloha.egg-info/not-zip-safe
apidev_djaloha.egg-info/requires.txt
apidev_djaloha.egg-info/top_level.txt
djaloha/__init__.py
djaloha/apps.py
djaloha/forms.py
djaloha/settings.py
djaloha/urls.py
djaloha/utils.py
djaloha/views.py
djaloha/widgets.py
djaloha/locale/fr/LC_MESSAGES/django.mo
djaloha/locale/fr/LC_MESSAGES/django.po
djaloha/static/aloha.0.22.6/build.txt
djaloha/static/aloha.0.22.6/package.json
djaloha/static/aloha.0.22.6/css/aloha-common-extra.css
djaloha/static/aloha.0.22.6/css/aloha-core.css
djaloha/static/aloha.0.22.6/css/aloha-reset.css
djaloha/static/aloha.0.22.6/css/aloha-sidebar.css
djaloha/static/aloha.0.22.6/css/aloha.css
djaloha/static/aloha.0.22.6/demo/block/dragdrop.html
djaloha/static/aloha.0.22.6/demo/block/index.css
djaloha/static/aloha.0.22.6/demo/block/index.html
djaloha/static/aloha.0.22.6/demo/block/blockdemo/css/block.css
djaloha/static/aloha.0.22.6/demo/block/blockdemo/img/stock-quote-aapl.gif
djaloha/static/aloha.0.22.6/demo/block/blockdemo/img/stock-quote-msft.gif
djaloha/static/aloha.0.22.6/demo/block/blockdemo/lib/block.js
djaloha/static/aloha.0.22.6/demo/block/blockdemo/lib/blockdemo-plugin.js
djaloha/static/aloha.0.22.6/demo/block/blockdemo/res/vcard.html
djaloha/static/aloha.0.22.6/demo/block/blockdemo/vendor/underscore.js
djaloha/static/aloha.0.22.6/demo/boilerplate/apple-touch-icon-114x114-precomposed.png
djaloha/static/aloha.0.22.6/demo/boilerplate/apple-touch-icon-57x57-precomposed.png
djaloha/static/aloha.0.22.6/demo/boilerplate/apple-touch-icon-72x72-precomposed.png
djaloha/static/aloha.0.22.6/demo/boilerplate/apple-touch-icon-precomposed.png
djaloha/static/aloha.0.22.6/demo/boilerplate/apple-touch-icon.png
djaloha/static/aloha.0.22.6/demo/boilerplate/captioned-image.html
djaloha/static/aloha.0.22.6/demo/boilerplate/crossdomain.xml
djaloha/static/aloha.0.22.6/demo/boilerplate/fake-jquery.js
djaloha/static/aloha.0.22.6/demo/boilerplate/favicon.ico
djaloha/static/aloha.0.22.6/demo/boilerplate/humans.txt
djaloha/static/aloha.0.22.6/demo/boilerplate/index.html
