Metadata-Version: 1.1
Name: apidev-djaloha
Version: 1.1.4
Summary: Django integration for aloha HTML5 editor
Home-page: https://github.com/ljean/djaloha/
Author: Luc Jean
Author-email: ljean@apidev.fr
License: BSD
Download-URL: https://github.com/ljean/djaloha/tarball/master
Platform: UNKNOWN
